termux_remember/__init__.py
termux_remember/auth.py
termux_remember/constants.py
termux_remember/main.py
termux_remember/memory.py
termux_remember/utils.py
termux_remember-1.1.2.dist-info/licenses/LICENSE
termux_remember-1.1.2.dist-info/METADATA
termux_remember-1.1.2.dist-info/WHEEL
termux_remember-1.1.2.dist-info/entry_points.txt
termux_remember-1.1.2.dist-info/top_level.txt
termux_remember-1.1.2.dist-info/RECORD
