Metadata-Version: 2.4
Name: termux-remember
Version: 1.1.2
Summary: A Secure and POSIX-style CLI Note Keeper for Termux Users with Tagging and Password Support
Home-page: https://github.com/mallikmusaddiq1/termux-remember
Author: Mallik Mohammad Musaddiq
Author-email: Mallik Mohammad Musaddiq <mallikmusaddiq1@gmail.com>
License: MIT
Project-URL: Homepage, https://github.com/mallikmusaddiq1/termux-remember
Project-URL: Repository, https://github.com/mallikmusaddiq1/termux-remember
Project-URL: Issues, https://github.com/mallikmusaddiq1/termux-remember/issues
Keywords: termux,notes,cli,secure,posix,tagging,password,remember
Classifier: Programming Language :: Python :: 3
Classifier: Operating System :: POSIX :: Linux
Classifier: License :: OSI Approved :: MIT License
Classifier: Environment :: Console
Classifier: Intended Audience :: End Users/Desktop
Classifier: Topic :: Utilities
Classifier: Topic :: Terminals
Requires-Python: >=3.7
License-File: LICENSE
Requires-Dist: rich>=13.0.0
Dynamic: author
Dynamic: home-page
Dynamic: license-file
Dynamic: requires-python
